README.txt
setup.py
instagram_filters/__init__.py
instagram_filters/filter.py
instagram_filters.egg-info/PKG-INFO
instagram_filters.egg-info/SOURCES.txt
instagram_filters.egg-info/dependency_links.txt
instagram_filters.egg-info/not-zip-safe
instagram_filters.egg-info/requires.txt
instagram_filters.egg-info/top_level.txt
instagram_filters/decorations/__init__.py
instagram_filters/decorations/border.py
instagram_filters/decorations/frame.py
instagram_filters/decorations/vignette.py
instagram_filters/filters/__init__.py
instagram_filters/filters/gotham.py
instagram_filters/filters/kelvin.py
instagram_filters/filters/lomo.py
instagram_filters/filters/nashville.py
instagram_filters/filters/toaster.py