Metadata-Version: 1.0
Name: instagram-filters
Version: 0.1
Summary: Instagram-like image filters
Home-page: https://github.com/acoomans/instagram-filters
Author: Arnaud Coomans
Author-email: arnaud.coomans@gmail.com
License: LICENSE.txt
Platform: UNKNOWN
